<?xml version="1.0" standalone="yes"?>
<LVData xmlns="http://www.ni.com/LVData">
	<Version>8.6.1</Version>
	<Cluster>
		<Name>ParserPreferences</Name>
		<NumElts>4</NumElts>
		<String>
			<Name>Macro</Name>
			<Val>database::store::Parser::output
database::store::Parser::preferences
database::store::cameraX::preferences
database::store::cameraX::storeMovie</Val>
		</String>
		<I32>
			<Name>TimeStamp</Name>
			<Val>30288856</Val>
		</I32>
		<Array>
			<Name>Submacros pathes</Name>
			<Dimsize>0</Dimsize>
			<Path>
				<Name>Path</Name>
				<Val/>
			</Path>
		</Array>
		<Array>
			<Name>Submacro array</Name>
			<Dimsize>0</Dimsize>
			<String>
				<Name>String</Name>
				<Val/>
			</String>
		</Array>
	</Cluster>
</LVData>
